apps/__init__.py
turbindo/__init__.py
turbindo/app.py
turbindo/configuration.py
turbindo/machine.py
turbindo/main.py
turbindo/util.py
turbindo/auth/__init__.py
turbindo/auth/user.py
turbindo/database/__init__.py
turbindo/database/base_object.py
turbindo/database/codegen.py
turbindo/database/preloader.py
turbindo/database/seralizers.py
turbindo/database/default/__init__.py
turbindo/database/default/accessors.py
turbindo/database/default/classes.py
turbindo/database/default/methods.py
turbindo/database/impl/__init__.py
turbindo/database/impl/gremlin/GraphDataTable.py
turbindo/database/impl/gremlin/__init__.py
turbindo/database/impl/sqlite/SqliteDataTable.py
turbindo/database/impl/sqlite/__init__.py
turbindo/database/impl/sqlite/methods.py
turbindo/database/impl/sqlite/sqlite_functions.py
turbindo/input_output/__init__.py
turbindo/input_output/aiodocker.py
turbindo/input_output/crypto.py
turbindo/input_output/docker.py
turbindo/input_output/shell.py
turbindo/log/__init__.py
turbindo/log/logger.py
turbindo/runtime/__init__.py
turbindo/runtime/exceptions.py
turbindo/runtime/instrumented_object.py
turbindo/runtime/io_context.py
turbindo/runtime/scheduler.py
turbindo/runtime/scheduler_methods.py
turbindo/runtime/tailrec.py
turbindo/server/__init__.py
turbindo/server/http.py
turbindo/server/ssh.py
turbindo/std/__init__.py
turbindo/std/math/__init__.py
turbindo/std/math/complex.py
turbindo/std/streams/__init__.py
turbindo/std/streams/stream.py
turbindo/templates/__init__.py
turbindo/templates/data_accessors.py.j2
turbindo/templates/skel/__init__.py
turbindo/templates/skel/data/__init__.py
turbindo/templates/skel/input_output/__init__.py
turbindo/templates/skel/jobs/__init__.py
turbindo/templates/skel/machine/__init__.py
turbindo/templates/skel/server/__init__.py
turbindo/templates/skel/tests/__init__.py
turbindo/test/__init__.py
turbindo/test/base_test.py
turbindo/test/test_system.py
turbindo/test/data/__init__.py
turbindo/test/data/accessors.py
turbindo-0.5.24.dist-info/METADATA
turbindo-0.5.24.dist-info/WHEEL
turbindo-0.5.24.dist-info/entry_points.txt
turbindo-0.5.24.dist-info/top_level.txt
turbindo-0.5.24.dist-info/RECORD
